{
  "summary": {
    "total_trades": 41,
    "winning_trades": 26,
    "losing_trades": 15,
    "win_rate": 63.41,
    "total_pnl": 12774.4,
    "total_pnl_percent": 13.99,
    "max_drawdown": 3.71,
    "max_drawdown_percent": 0.04,
    "avg_win": 836.89,
    "avg_loss": 598.98,
    "profit_factor": 2.42,
    "expectancy": 311.5707,
    "sharpe_ratio": 6.11,
    "sortino_ratio": 6.9,
    "avg_bars_held": 66.3,
    "max_consecutive_wins": 4,
    "max_consecutive_losses": 3,
    "signal_performance": {
      "predictive_breakout_long": {
        "total": 17,
        "wins": 12,
        "win_rate": 0.7058823529411765,
        "total_pnl": 5740.3999999999505,
        "avg_pnl": 337.67058823529123
      },
      "predictive_breakout_short": {
        "total": 24,
        "wins": 14,
        "win_rate": 0.5833333333333334,
        "total_pnl": 7033.999999999942,
        "avg_pnl": 293.0833333333309
      }
    }
  },
  "trades": [
    {
      "entry_time": "2025-12-01T19:15:00",
      "exit_time": "2025-12-01T22:30:00",
      "entry_price": 85448.5,
      "exit_price": 86399.9,
      "direction": "long",
      "signal_type": "predictive_breakout_long",
      "signal_confidence": 0.6959795007213507,
      "pnl": 951.3999999999942,
      "pnl_percent": 1.1134191940174423,
      "bars_held": 39,
      "exit_reason": "take_profit",
      "max_favorable": 951.3999999999942,
      "max_adverse": -751.3000000000029
    },
    {
      "entry_time": "2025-12-01T22:55:00",
      "exit_time": "2025-12-02T08:55:00",
      "entry_price": 86380.1,
      "exit_price": 86965.0,
      "direction": "long",
      "signal_type": "predictive_breakout_long",
      "signal_confidence": 0.6936589280014898,
      "pnl": 584.8999999999942,
      "pnl_percent": 0.6771235504473764,
      "bars_held": 120,
      "exit_reason": "max_hold",
      "max_favorable": 755.7999999999884,
      "max_adverse": -189.0
    },
    {
      "entry_time": "2025-12-02T09:15:00",
      "exit_time": "2025-12-02T12:25:00",
      "entry_price": 86518.9,
      "exit_price": 87386.7,
      "direction": "short",
      "signal_type": "predictive_breakout_short",
      "signal_confidence": 0.6622917489242683,
      "pnl": -867.8000000000029,
      "pnl_percent": -1.0030178377210102,
      "bars_held": 38,
      "exit_reason": "stop_loss",
      "max_favorable": 121.69999999999709,
      "max_adverse": -867.8000000000029
    },
    {
      "entry_time": "2025-12-02T12:25:00",
      "exit_time": "2025-12-02T15:10:00",
      "entry_price": 87386.7,
      "exit_price": 88297.7,
      "direction": "long",
      "signal_type": "predictive_breakout_long",
      "signal_confidence": 0.6432692264053308,
      "pnl": 911.0,
      "pnl_percent": 1.0424927363088432,
      "bars_held": 33,
      "exit_reason": "take_profit",
      "max_favorable": 911.0,
      "max_adverse": -337.59999999999127
    },
    {
      "entry_time": "2025-12-02T15:20:00",
      "exit_time": "2025-12-02T16:00:00",
      "entry_price": 88521.1,
      "exit_price": 89970.5,
      "direction": "long",
      "signal_type": "predictive_breakout_long",
      "signal_confidence": 0.6003690617094888,
      "pnl": 1449.3999999999942,
      "pnl_percent": 1.6373497392147118,
      "bars_held": 8,
      "exit_reason": "take_profit",
      "max_favorable": 1449.3999999999942,
      "max_adverse": 0.0
    },
    {
      "entry_time": "2025-12-02T23:00:00",
      "exit_time": "2025-12-03T03:10:00",
      "entry_price": 91794.0,
      "exit_price": 92841.0,
      "direction": "long",
      "signal_type": "predictive_breakout_long",
      "signal_confidence": 0.65,
      "pnl": 1047.0,
      "pnl_percent": 1.140597424668279,
      "bars_held": 50,
      "exit_reason": "take_profit",
      "max_favorable": 1047.0,
      "max_adverse": -774.1000000000058
    },
    {
      "entry_time": "2025-12-03T03:10:00",
      "exit_time": "2025-12-03T07:05:00",
      "entry_price": 92841.0,
      "exit_price": 93769.8,
      "direction": "long",
      "signal_type": "predictive_breakout_long",
      "signal_confidence": 0.6365184100889906,
      "pnl": 928.8000000000029,
      "pnl_percent": 1.0004200730280834,
      "bars_held": 47,
      "exit_reason": "take_profit",
      "max_favorable": 928.8000000000029,
      "max_adverse": -355.3999999999942
    },
    {
      "entry_time": "2025-12-03T07:05:00",
      "exit_time": "2025-12-03T08:15:00",
      "entry_price": 93769.8,
      "exit_price": 92830.4,
      "direction": "long",
      "signal_type": "predictive_breakout_long",
      "signal_confidence": 0.65,
      "pnl": -939.4000000000087,
      "pnl_percent": -1.0018150833210786,
      "bars_held": 14,
      "exit_reason": "stop_loss",
      "max_favorable": 138.6999999999971,
      "max_adverse": -939.4000000000087
    },
    {
      "entry_time": "2025-12-03T08:25:00",
      "exit_time": "2025-12-03T15:00:00",
      "entry_price": 92995.9,
      "exit_price": 91702.9,
      "direction": "short",
      "signal_type": "predictive_breakout_short",
      "signal_confidence": 0.6130443031703044,
      "pnl": 1293.0,
      "pnl_percent": 1.3903838771386696,
      "bars_held": 79,
      "exit_reason": "take_profit",
      "max_favorable": 1293.0,
      "max_adverse": -306.20000000001164
    },
    {
      "entry_time": "2025-12-03T18:10:00",
      "exit_time": "2025-12-03T22:55:00",
      "entry_price": 92587.0,
      "exit_price": 93645.0,
      "direction": "long",
      "signal_type": "predictive_breakout_long",
      "signal_confidence": 0.6,
      "pnl": 1058.0,
      "pnl_percent": 1.1427090196247853,
      "bars_held": 57,
      "exit_reason": "take_profit",
      "max_favorable": 1058.0,
      "max_adverse": -366.8999999999942
    },
    {
      "entry_time": "2025-12-04T00:50:00",
      "exit_time": "2025-12-04T01:30:00",
      "entry_price": 93597.4,
      "exit_price": 92630.0,
      "direction": "short",
      "signal_type": "predictive_breakout_short",
      "signal_confidence": 0.6494915362450016,
      "pnl": 967.3999999999942,
      "pnl_percent": 1.0335757189836408,
      "bars_held": 8,
      "exit_reason": "take_profit",
      "max_favorable": 967.3999999999942,
      "max_adverse": 0.0
    },
    {
      "entry_time": "2025-12-04T02:35:00",
      "exit_time": "2025-12-04T12:35:00",
      "entry_price": 93456.0,
      "exit_price": 92808.0,
      "direction": "long",
      "signal_type": "predictive_breakout_long",
      "signal_confidence": 0.6343906029554058,
      "pnl": -648.0,
      "pnl_percent": -0.6933744221879815,
      "bars_held": 120,
      "exit_reason": "max_hold",
      "max_favorable": 518.3000000000029,
      "max_adverse": -741.8999999999942
    },
    {
      "entry_time": "2025-12-04T14:55:00",
      "exit_time": "2025-12-04T20:10:00",
      "entry_price": 92480.4,
      "exit_price": 91243.0,
      "direction": "short",
      "signal_type": "predictive_breakout_short",
      "signal_confidence": 0.6,
      "pnl": 1237.3999999999942,
      "pnl_percent": 1.338013243887347,
      "bars_held": 63,
      "exit_reason": "take_profit",
      "max_favorable": 1237.3999999999942,
      "max_adverse": -719.5
    },
    {
      "entry_time": "2025-12-04T20:10:00",
      "exit_time": "2025-12-04T21:35:00",
      "entry_price": 91243.0,
      "exit_price": 92158.1,
      "direction": "short",
      "signal_type": "predictive_breakout_short",
      "signal_confidence": 0.6134557749661743,
      "pnl": -915.1000000000058,
      "pnl_percent": -1.0029262518768627,
      "bars_held": 17,
      "exit_reason": "stop_loss",
      "max_favorable": 341.6999999999971,
      "max_adverse": -915.1000000000058
    },
    {
      "entry_time": "2025-12-04T22:55:00",
      "exit_time": "2025-12-05T08:55:00",
      "entry_price": 92111.2,
      "exit_price": 92227.5,
      "direction": "short",
      "signal_type": "predictive_breakout_short",
      "signal_confidence": 0.6132128306019677,
      "pnl": -116.30000000000291,
      "pnl_percent": -0.12626043304180481,
      "bars_held": 120,
      "exit_reason": "max_hold",
      "max_favorable": 296.6999999999971,
      "max_adverse": -506.8000000000029
    },
    {
      "entry_time": "2025-12-05T09:15:00",
      "exit_time": "2025-12-05T10:40:00",
      "entry_price": 92011.9,
      "exit_price": 91014.3,
      "direction": "short",
      "signal_type": "predictive_breakout_short",
      "signal_confidence": 0.75,
      "pnl": 997.5999999999913,
      "pnl_percent": 1.0842075861926461,
      "bars_held": 17,
      "exit_reason": "take_profit",
      "max_favorable": 997.5999999999913,
      "max_adverse": -68.10000000000582
    },
    {
      "entry_time": "2025-12-05T10:50:00",
      "exit_time": "2025-12-05T15:45:00",
      "entry_price": 91003.6,
      "exit_price": 90054.1,
      "direction": "short",
      "signal_type": "predictive_breakout_short",
      "signal_confidence": 0.6146247892654668,
      "pnl": 949.5,
      "pnl_percent": 1.0433653174160142,
      "bars_held": 59,
      "exit_reason": "take_profit",
      "max_favorable": 949.5,
      "max_adverse": -472.3999999999942
    },
    {
      "entry_time": "2025-12-05T22:45:00",
      "exit_time": "2025-12-06T08:45:00",
      "entry_price": 89120.7,
      "exit_price": 89620.1,
      "direction": "short",
      "signal_type": "predictive_breakout_short",
      "signal_confidence": 0.6784230437493739,
      "pnl": -499.40000000000873,
      "pnl_percent": -0.5603636416679949,
      "bars_held": 120,
      "exit_reason": "max_hold",
      "max_favorable": 202.0,
      "max_adverse": -600.1999999999971
    },
    {
      "entry_time": "2025-12-06T11:45:00",
      "exit_time": "2025-12-06T21:45:00",
      "entry_price": 89463.2,
      "exit_price": 89501.5,
      "direction": "short",
      "signal_type": "predictive_breakout_short",
      "signal_confidence": 0.6259846661857333,
      "pnl": -38.30000000000291,
      "pnl_percent": -0.04281089878296653,
      "bars_held": 120,
      "exit_reason": "max_hold",
      "max_favorable": 171.09999999999127,
      "max_adverse": -565.8000000000029
    },
    {
      "entry_time": "2025-12-06T23:00:00",
      "exit_time": "2025-12-07T09:00:00",
      "entry_price": 89345.9,
      "exit_price": 89243.1,
      "direction": "short",
      "signal_type": "predictive_breakout_short",
      "signal_confidence": 0.6,
      "pnl": 102.79999999998836,
      "pnl_percent": 0.11505844140580414,
      "bars_held": 120,
      "exit_reason": "max_hold",
      "max_favorable": 439.0,
      "max_adverse": -354.0
    },
    {
      "entry_time": "2025-12-07T13:40:00",
      "exit_time": "2025-12-07T15:20:00",
      "entry_price": 89277.0,
      "exit_price": 88337.9,
      "direction": "long",
      "signal_type": "predictive_breakout_long",
      "signal_confidence": 0.6463375735607241,
      "pnl": -939.1000000000058,
      "pnl_percent": -1.0518946649193026,
      "bars_held": 20,
      "exit_reason": "stop_loss",
      "max_favorable": 201.3000000000029,
      "max_adverse": -939.1000000000058
    },
    {
      "entry_time": "2025-12-07T21:30:00",
      "exit_time": "2025-12-07T22:45:00",
      "entry_price": 91324.8,
      "exit_price": 90215.7,
      "direction": "long",
      "signal_type": "predictive_breakout_long",
      "signal_confidence": 0.65,
      "pnl": -1109.1000000000058,
      "pnl_percent": -1.2144565331651487,
      "bars_held": 15,
      "exit_reason": "stop_loss",
      "max_favorable": 123.69999999999709,
      "max_adverse": -1109.1000000000058
    },
    {
      "entry_time": "2025-12-07T23:00:00",
      "exit_time": "2025-12-08T02:25:00",
      "entry_price": 89861.5,
      "exit_price": 91091.0,
      "direction": "short",
      "signal_type": "predictive_breakout_short",
      "signal_confidence": 0.646831032751315,
      "pnl": -1229.5,
      "pnl_percent": -1.3682166445029296,
      "bars_held": 41,
      "exit_reason": "stop_loss",
      "max_favorable": 614.8000000000029,
      "max_adverse": -1229.5
    },
    {
      "entry_time": "2025-12-08T02:30:00",
      "exit_time": "2025-12-08T12:30:00",
      "entry_price": 91309.6,
      "exit_price": 91867.8,
      "direction": "long",
      "signal_type": "predictive_breakout_long",
      "signal_confidence": 0.6047894599170861,
      "pnl": 558.1999999999971,
      "pnl_percent": 0.6113267389190152,
      "bars_held": 120,
      "exit_reason": "max_hold",
      "max_favorable": 850.5,
      "max_adverse": -483.70000000001164
    },
    {
      "entry_time": "2025-12-08T13:10:00",
      "exit_time": "2025-12-08T15:55:00",
      "entry_price": 91739.9,
      "exit_price": 90809.0,
      "direction": "short",
      "signal_type": "predictive_breakout_short",
      "signal_confidence": 0.6745048034504533,
      "pnl": 930.8999999999942,
      "pnl_percent": 1.0147166064057125,
      "bars_held": 33,
      "exit_reason": "take_profit",
      "max_favorable": 930.8999999999942,
      "max_adverse": -103.30000000000291
    },
    {
      "entry_time": "2025-12-09T00:15:00",
      "exit_time": "2025-12-09T04:15:00",
      "entry_price": 90744.0,
      "exit_price": 89817.2,
      "direction": "short",
      "signal_type": "predictive_breakout_short",
      "signal_confidence": 0.6,
      "pnl": 926.8000000000029,
      "pnl_percent": 1.0213347438949163,
      "bars_held": 48,
      "exit_reason": "take_profit",
      "max_favorable": 926.8000000000029,
      "max_adverse": 0.0
    },
    {
      "entry_time": "2025-12-09T04:15:00",
      "exit_time": "2025-12-09T14:15:00",
      "entry_price": 89817.2,
      "exit_price": 90536.4,
      "direction": "short",
      "signal_type": "predictive_breakout_short",
      "signal_confidence": 0.7428822978432511,
      "pnl": -719.1999999999971,
      "pnl_percent": -0.8007374979402577,
      "bars_held": 120,
      "exit_reason": "max_hold",
      "max_favorable": 82.89999999999418,
      "max_adverse": -785.0
    },
    {
      "entry_time": "2025-12-09T14:20:00",
      "exit_time": "2025-12-09T16:35:00",
      "entry_price": 90598.8,
      "exit_price": 91554.2,
      "direction": "long",
      "signal_type": "predictive_breakout_long",
      "signal_confidence": 0.65,
      "pnl": 955.3999999999942,
      "pnl_percent": 1.054539353722118,
      "bars_held": 27,
      "exit_reason": "take_profit",
      "max_favorable": 955.3999999999942,
      "max_adverse": -561.1999999999971
    },
    {
      "entry_time": "2025-12-09T21:15:00",
      "exit_time": "2025-12-09T22:50:00",
      "entry_price": 93288.8,
      "exit_price": 92240.9,
      "direction": "short",
      "signal_type": "predictive_breakout_short",
      "signal_confidence": 0.6,
      "pnl": 1047.9000000000087,
      "pnl_percent": 1.1232859678761102,
      "bars_held": 19,
      "exit_reason": "take_profit",
      "max_favorable": 1047.9000000000087,
      "max_adverse": 0.0
    },
    {
      "entry_time": "2025-12-10T00:40:00",
      "exit_time": "2025-12-10T10:40:00",
      "entry_price": 92902.2,
      "exit_price": 92560.0,
      "direction": "long",
      "signal_type": "predictive_breakout_long",
      "signal_confidence": 0.7000000000000001,
      "pnl": -342.1999999999971,
      "pnl_percent": -0.36834434491324974,
      "bars_held": 120,
      "exit_reason": "max_hold",
      "max_favorable": 0.0,
      "max_adverse": -915.6999999999971
    },
    {
      "entry_time": "2025-12-10T10:40:00",
      "exit_time": "2025-12-10T20:40:00",
      "entry_price": 92560.0,
      "exit_price": 92538.5,
      "direction": "short",
      "signal_type": "predictive_breakout_short",
      "signal_confidence": 0.6248592222915368,
      "pnl": 21.5,
      "pnl_percent": 0.02322817631806396,
      "bars_held": 120,
      "exit_reason": "max_hold",
      "max_favorable": 862.6000000000058,
      "max_adverse": -523.8000000000029
    },
    {
      "entry_time": "2025-12-11T01:25:00",
      "exit_time": "2025-12-11T02:15:00",
      "entry_price": 91731.7,
      "exit_price": 90755.6,
      "direction": "short",
      "signal_type": "predictive_breakout_short",
      "signal_confidence": 0.7365523194307675,
      "pnl": 976.0999999999913,
      "pnl_percent": 1.0640814462176014,
      "bars_held": 10,
      "exit_reason": "take_profit",
      "max_favorable": 976.0999999999913,
      "max_adverse": 0.0
    },
    {
      "entry_time": "2025-12-11T05:40:00",
      "exit_time": "2025-12-11T15:40:00",
      "entry_price": 90061.3,
      "exit_price": 90231.7,
      "direction": "long",
      "signal_type": "predictive_breakout_long",
      "signal_confidence": 0.7000000000000001,
      "pnl": 170.39999999999418,
      "pnl_percent": 0.18920446407057656,
      "bars_held": 120,
      "exit_reason": "max_hold",
      "max_favorable": 326.5,
      "max_adverse": -170.10000000000582
    },
    {
      "entry_time": "2025-12-11T19:35:00",
      "exit_time": "2025-12-11T21:40:00",
      "entry_price": 90530.0,
      "exit_price": 91535.4,
      "direction": "long",
      "signal_type": "predictive_breakout_long",
      "signal_confidence": 0.6077313095328958,
      "pnl": 1005.3999999999942,
      "pnl_percent": 1.1105710814094711,
      "bars_held": 25,
      "exit_reason": "take_profit",
      "max_favorable": 1005.3999999999942,
      "max_adverse": 0.0
    },
    {
      "entry_time": "2025-12-12T01:45:00",
      "exit_time": "2025-12-12T11:45:00",
      "entry_price": 92164.2,
      "exit_price": 92499.9,
      "direction": "short",
      "signal_type": "predictive_breakout_short",
      "signal_confidence": 0.8,
      "pnl": -335.6999999999971,
      "pnl_percent": -0.3642412129655518,
      "bars_held": 120,
      "exit_reason": "max_hold",
      "max_favorable": 643.1999999999971,
      "max_adverse": -491.90000000000873
    },
    {
      "entry_time": "2025-12-12T12:35:00",
      "exit_time": "2025-12-12T16:25:00",
      "entry_price": 92278.4,
      "exit_price": 90795.0,
      "direction": "short",
      "signal_type": "predictive_breakout_short",
      "signal_confidence": 0.75,
      "pnl": 1483.3999999999942,
      "pnl_percent": 1.6075267885008782,
      "bars_held": 46,
      "exit_reason": "take_profit",
      "max_favorable": 1483.3999999999942,
      "max_adverse": -257.0
    },
    {
      "entry_time": "2025-12-12T20:40:00",
      "exit_time": "2025-12-13T06:40:00",
      "entry_price": 90077.0,
      "exit_price": 90236.6,
      "direction": "short",
      "signal_type": "predictive_breakout_short",
      "signal_confidence": 0.65,
      "pnl": -159.60000000000582,
      "pnl_percent": -0.1771817445074834,
      "bars_held": 120,
      "exit_reason": "max_hold",
      "max_favorable": 161.0,
      "max_adverse": -305.6999999999971
    },
    {
      "entry_time": "2025-12-13T07:20:00",
      "exit_time": "2025-12-13T17:20:00",
      "entry_price": 90249.0,
      "exit_price": 90058.4,
      "direction": "short",
      "signal_type": "predictive_breakout_short",
      "signal_confidence": 0.75,
      "pnl": 190.60000000000582,
      "pnl_percent": 0.21119347582799347,
      "bars_held": 120,
      "exit_reason": "max_hold",
      "max_favorable": 327.1000000000058,
      "max_adverse": -315.8000000000029
    },
    {
      "entry_time": "2025-12-13T19:10:00",
      "exit_time": "2025-12-14T05:10:00",
      "entry_price": 90143.9,
      "exit_price": 90242.2,
      "direction": "long",
      "signal_type": "predictive_breakout_long",
      "signal_confidence": 0.6745045285919588,
      "pnl": 98.30000000000291,
      "pnl_percent": 0.10904786679964248,
      "bars_held": 120,
      "exit_reason": "max_hold",
      "max_favorable": 280.1000000000058,
      "max_adverse": -218.0
    },
    {
      "entry_time": "2025-12-14T05:10:00",
      "exit_time": "2025-12-14T12:35:00",
      "entry_price": 90242.2,
      "exit_price": 89326.2,
      "direction": "short",
      "signal_type": "predictive_breakout_short",
      "signal_confidence": 0.65,
      "pnl": 916.0,
      "pnl_percent": 1.015046175735964,
      "bars_held": 89,
      "exit_reason": "take_profit",
      "max_favorable": 916.0,
      "max_adverse": -46.60000000000582
    },
    {
      "entry_time": "2025-12-14T23:35:00",
      "exit_time": "2025-12-15T00:55:00",
      "entry_price": 87992.8,
      "exit_price": 88118.8,
      "direction": "short",
      "signal_type": "predictive_breakout_short",
      "signal_confidence": 0.6139623683935346,
      "pnl": -126.0,
      "pnl_percent": -0.14319353401641952,
      "bars_held": 16,
      "exit_reason": "backtest_end",
      "max_favorable": 87.40000000000873,
      "max_adverse": -377.3999999999942
    }
  ],
  "config": {
    "topology_window": 100,
    "predictive_window": 200,
    "min_confidence": 0.6,
    "stop_loss_pct": 1.0,
    "take_profit_pct": 1.0,
    "initial_capital": 10000
  }
}